capywfa/__init__.py
capywfa/capywfa.py
capywfa/cdx_support.py
capywfa/lst_to_sbom.py
capywfa/verify_sources.py
capywfa-0.9.3.dist-info/LICENSE
capywfa-0.9.3.dist-info/LICENSES/MIT.txt
capywfa-0.9.3.dist-info/METADATA
capywfa-0.9.3.dist-info/WHEEL
capywfa-0.9.3.dist-info/entry_points.txt
capywfa-0.9.3.dist-info/RECORD
